tf2_bert/__init__.py
tf2_bert/activation.py
tf2_bert/layers.py
tf2_bert/models.py
tf2_bert/tokenizers.py
tf2_bert-0.11.dist-info/LICENSE
tf2_bert-0.11.dist-info/METADATA
tf2_bert-0.11.dist-info/WHEEL
tf2_bert-0.11.dist-info/top_level.txt
tf2_bert-0.11.dist-info/RECORD
