Metadata-Version: 2.1
Name: tf2-bert
Version: 0.11
Summary: tf2_bert
Home-page: https://github.com/Qinbf/tf2_bert
Author: QinBingFeng
Author-email: 114479602@qq.com
License: UNKNOWN
Platform: UNKNOWN
